clapify/__init__.py
clapify-0.0.1.dist-info/METADATA
clapify-0.0.1.dist-info/RECORD
clapify-0.0.1.dist-info/WHEEL
clapify-0.0.1.dist-info/top_level.txt
