Metadata-Version: 2.1
Name: clapify
Version: 0.0.1
Summary: Emphasize everything with a hand-clapping emoji!
Home-page: UNKNOWN
Author: Aviad Rom
Author-email: UNKNOWN
License: UNKNOWN
Platform: UNKNOWN
Classifier: License :: OSI Approved :: MIT License
Classifier: Programming Language :: Python
